freexegol.py
freexegol-0.2.4.dist-info/licenses/LICENSE
freexegol-0.2.4.dist-info/METADATA
freexegol-0.2.4.dist-info/WHEEL
freexegol-0.2.4.dist-info/entry_points.txt
freexegol-0.2.4.dist-info/top_level.txt
freexegol-0.2.4.dist-info/RECORD
