Metadata-Version: 2.4
Name: freexegol
Version: 0.2.4
Summary: A free and open-source Python wrapper for Docker, available for lifetime use and permitted for commercial applications.
Author-email: ProcessusT <processus@thiefin.fr>
License: GNU GENERAL PUBLIC LICENSE
Project-URL: Homepage, https://github.com/ProcessusT/freexegol
Requires-Python: >=3.8
License-File: LICENSE
Requires-Dist: docker
Requires-Dist: gitpython
Dynamic: license-file
